ai_assistant_provider/__init__.py
ai_assistant_provider/ai_assistant_provider.py
ai_assistant_provider-0.0.7.dist-info/licenses/LICENSE
ai_assistant_provider-0.0.7.dist-info/METADATA
ai_assistant_provider-0.0.7.dist-info/WHEEL
ai_assistant_provider-0.0.7.dist-info/top_level.txt
ai_assistant_provider-0.0.7.dist-info/RECORD
